FrontalLobe.py
FrontalLobe-0.0.2.1.dist-info/METADATA
FrontalLobe-0.0.2.1.dist-info/WHEEL
FrontalLobe-0.0.2.1.dist-info/top_level.txt
FrontalLobe-0.0.2.1.dist-info/RECORD
