Metadata-Version: 2.1
Name: FrontalLobe
Version: 0.0.2.1
Summary: Artificial Neural Network classifier
Home-page: https://github.com/Achyut-sudo/FrontalLobe
Author: Achyut Madhawan (gitHub: Achyut-sudo)
Author-email: achyut.madhawan@gmail.com
License: UNKNOWN
Keywords: python,Artificial Neural Networks,classifier,Confusion Matrix,Nueral Net
Platform: UNKNOWN
Classifier: Development Status :: 2 - Pre-Alpha
Classifier: Intended Audience :: Education
Classifier: Topic :: Software Development :: Libraries :: Python Modules
Classifier: Programming Language :: Python :: 3.6
Classifier: Programming Language :: Python :: 3.7
Classifier: Programming Language :: Python :: 3.8
Classifier: Programming Language :: Python :: 3.9
Classifier: Programming Language :: Python :: 3.10
Classifier: Programming Language :: Python :: Implementation
Classifier: Operating System :: OS Independent
Requires-Python: >=3.6
Requires-Dist: numpy
Requires-Dist: tabulate
Requires-Dist: matplotlib
Requires-Dist: pandas
Requires-Dist: reprint
